azure_storage/__init__.py
azure_storage/storage.py
django_azure_storage-0.20.1.dist-info/DESCRIPTION.rst
django_azure_storage-0.20.1.dist-info/METADATA
django_azure_storage-0.20.1.dist-info/RECORD
django_azure_storage-0.20.1.dist-info/WHEEL
django_azure_storage-0.20.1.dist-info/metadata.json
django_azure_storage-0.20.1.dist-info/top_level.txt
